flair/__init__.py
flair/class_utils.py
flair/data.py
flair/distributed_utils.py
flair/file_utils.py
flair/inference_utils.py
flair/optim.py
flair/py.typed
flair/samplers.py
flair/splitter.py
flair/tokenization.py
flair/training_utils.py
flair/__pycache__/__init__.cpython-38.pyc
flair/__pycache__/__init__.cpython-39.pyc
flair/__pycache__/data.cpython-38.pyc
flair/__pycache__/data.cpython-39.pyc
flair/__pycache__/file_utils.cpython-38.pyc
flair/__pycache__/file_utils.cpython-39.pyc
flair/datasets/__init__.py
flair/datasets/base.py
flair/datasets/biomedical.py
flair/datasets/document_classification.py
flair/datasets/entity_linking.py
flair/datasets/ocr.py
flair/datasets/relation_extraction.py
flair/datasets/sequence_labeling.py
flair/datasets/text_image.py
flair/datasets/text_text.py
flair/datasets/treebanks.py
flair/datasets/__pycache__/__init__.cpython-38.pyc
flair/datasets/__pycache__/__init__.cpython-39.pyc
flair/datasets/__pycache__/base.cpython-38.pyc
flair/datasets/__pycache__/base.cpython-39.pyc
flair/datasets/__pycache__/biomedical.cpython-38.pyc
flair/datasets/__pycache__/biomedical.cpython-39.pyc
flair/datasets/__pycache__/document_classification.cpython-38.pyc
flair/datasets/__pycache__/document_classification.cpython-39.pyc
flair/datasets/__pycache__/entity_linking.cpython-38.pyc
flair/datasets/__pycache__/entity_linking.cpython-39.pyc
flair/datasets/__pycache__/ocr.cpython-38.pyc
flair/datasets/__pycache__/ocr.cpython-39.pyc
flair/datasets/__pycache__/relation_extraction.cpython-38.pyc
flair/datasets/__pycache__/relation_extraction.cpython-39.pyc
flair/datasets/__pycache__/sequence_labeling.cpython-38.pyc
flair/datasets/__pycache__/sequence_labeling.cpython-39.pyc
flair/datasets/__pycache__/text_image.cpython-38.pyc
flair/datasets/__pycache__/text_image.cpython-39.pyc
flair/datasets/__pycache__/text_text.cpython-38.pyc
flair/datasets/__pycache__/text_text.cpython-39.pyc
flair/datasets/__pycache__/treebanks.cpython-38.pyc
flair-0.15.0.dist-info/LICENSE
flair-0.15.0.dist-info/METADATA
flair-0.15.0.dist-info/WHEEL
flair-0.15.0.dist-info/top_level.txt
flair-0.15.0.dist-info/RECORD
