Metadata-Version: 2.1
Name: flair
Version: 0.15.0
Summary: A very simple framework for state-of-the-art NLP
Home-page: https://github.com/flairNLP/flair
Author: Alan Akbik
Author-email: alan.akbik@gmail.com
License: MIT
Requires-Python: >=3.9
License-File: LICENSE
Requires-Dist: boto3>=1.20.27
Requires-Dist: conllu<5.0.0,>=4.0
Requires-Dist: deprecated>=1.2.13
Requires-Dist: ftfy>=6.1.0
Requires-Dist: gdown>=4.4.0
Requires-Dist: huggingface-hub>=0.10.0
Requires-Dist: langdetect>=1.0.9
Requires-Dist: lxml>=4.8.0
Requires-Dist: matplotlib>=2.2.3
Requires-Dist: more-itertools>=8.13.0
Requires-Dist: mpld3>=0.3
Requires-Dist: pptree>=3.1
Requires-Dist: python-dateutil>=2.8.2
Requires-Dist: pytorch-revgrad>=0.2.0
Requires-Dist: regex>=2022.1.18
Requires-Dist: scikit-learn>=1.0.2
Requires-Dist: segtok>=1.5.11
Requires-Dist: sqlitedict>=2.0.0
Requires-Dist: tabulate>=0.8.10
Requires-Dist: torch!=1.8,>=1.5.0
Requires-Dist: tqdm>=4.63.0
Requires-Dist: transformer-smaller-training-vocab>=0.2.3
Requires-Dist: transformers[sentencepiece]<5.0.0,>=4.25.0
Requires-Dist: wikipedia-api>=0.5.7
Requires-Dist: bioc<3.0.0,>=2.0.0
Provides-Extra: word-embeddings
Requires-Dist: gensim>=4.2.0; extra == "word-embeddings"
Requires-Dist: bpemb>=0.3.5; extra == "word-embeddings"
